yipao/__init__.py
yipao/LLM/__init__.py
yipao/LLM/customllm.py
yipao/LLM/gemini.py
yipao/LLM/vertex.py
yipao/agent/__init__.py
yipao/agent/core.py
yipao/databases/__init__.py
yipao/databases/mysql.py
yipao/prompts/__init__.py
yipao/prompts/builder.py
yipao/prompts/prompts.py
yipao/retrievers/__init__.py
yipao/retrievers/vectorStoreRetriever.py
yipao/utils/__init__.py
yipao/utils/constants.py
yipao/utils/logger.py
yipao/utils/utils.py
yipao/vectorstores/__init__.py
yipao/vectorstores/chromadb.py
yipao/vectorstores/qdrant.py
yipao-0.0.4.dist-info/METADATA
yipao-0.0.4.dist-info/WHEEL
yipao-0.0.4.dist-info/RECORD
