Metadata-Version: 2.3
Name: yipao
Version: 0.0.4
Summary: Yipao is a library enabling AI-driven interactions with SQL databases, facilitating dynamic SQL query generation and execution.
Project-URL: Homepage, https://facil-pos.github.io/yipao/
Project-URL: Development, https://github.com/facil-pos/yipao
Author-email: factral <nelsonfabiancs8@gmail.com>, Daniel <manosalvasierra@gmail.com>
License: MIT License
Keywords: ai,database,dynamic,execution,generation,query,rag,sql
Classifier: License :: OSI Approved :: MIT License
Classifier: Operating System :: OS Independent
Classifier: Programming Language :: Python
Classifier: Programming Language :: Python :: 3.8
Classifier: Programming Language :: Python :: 3.9
Classifier: Programming Language :: Python :: 3.10
Classifier: Programming Language :: Python :: 3.11
Classifier: Programming Language :: Python :: 3.12
Classifier: Topic :: Scientific/Engineering
Requires-Python: >=3
Requires-Dist: google-generativeai
Requires-Dist: pandas
Requires-Dist: pymysql
Requires-Dist: qdrant-client[fastembed]
Requires-Dist: vertexai
Provides-Extra: chroma
Requires-Dist: chromadb; extra == 'chroma'
Provides-Extra: doc
Requires-Dist: sphinx; extra == 'doc'
Requires-Dist: sphinx-autodoc-annotation; extra == 'doc'
Requires-Dist: sphinx-autodoc-typehints; extra == 'doc'
Requires-Dist: sphinxawesome-theme; extra == 'doc'
